MANIFEST.in
setup.py
src/infi/__init__.py
src/infi.nose_html_output.egg-info/PKG-INFO
src/infi.nose_html_output.egg-info/SOURCES.txt
src/infi.nose_html_output.egg-info/dependency_links.txt
src/infi.nose_html_output.egg-info/entry_points.txt
src/infi.nose_html_output.egg-info/namespace_packages.txt
src/infi.nose_html_output.egg-info/not-zip-safe
src/infi.nose_html_output.egg-info/requires.txt
src/infi.nose_html_output.egg-info/top_level.txt
src/infi/nose_html_output/__init__.py
src/infi/nose_html_output/__version__.py
src/infi/nose_html_output/ajax.py
src/infi/nose_html_output/static/ajax_reload.js
src/infi/nose_html_output/static/index.css
src/infi/nose_html_output/static/index.js
src/infi/nose_html_output/static/jquery-1.8.0.min.js
src/infi/nose_html_output/static/spin.min.js
src/infi/nose_html_output/static/spinner.factory.js