Metadata-Version: 1.0
Name: infi.nose_html_output
Version: 0.1.12
Summary: HTML Plugin for Nose
Home-page: https://github.com/Infinidat/infi.nose_html_output
Author: Arnon Yaari
Author-email: arnony@infinidat.com
License: PSF
Platform: UNKNOWN
Classifier: Intended Audience :: Developers
Classifier: Intended Audience :: System Administrators
Classifier: License :: OSI Approved :: Python Software Foundation License
Classifier: Operating System :: OS Independent
Classifier: Programming Language :: Python
Classifier: Topic :: Software Development :: Libraries :: Python Modules
